odoo/addons/l10n_th_amount_to_text/README.rst
odoo/addons/l10n_th_amount_to_text/__init__.py
odoo/addons/l10n_th_amount_to_text/__manifest__.py
odoo/addons/l10n_th_amount_to_text/i18n/l10n_th_amount_to_text.pot
odoo/addons/l10n_th_amount_to_text/i18n/th.po
odoo/addons/l10n_th_amount_to_text/models/__init__.py
odoo/addons/l10n_th_amount_to_text/models/res_currency.py
odoo/addons/l10n_th_amount_to_text/readme/CONFIGURE.rst
odoo/addons/l10n_th_amount_to_text/readme/CONTRIBUTORS.rst
odoo/addons/l10n_th_amount_to_text/readme/DESCRIPTION.rst
odoo/addons/l10n_th_amount_to_text/readme/USAGE.rst
odoo/addons/l10n_th_amount_to_text/static/description/icon.png
odoo/addons/l10n_th_amount_to_text/static/description/index.html
odoo/addons/l10n_th_amount_to_text/tests/__init__.py
odoo/addons/l10n_th_amount_to_text/tests/test_amount_to_text.py
odoo14_addon_l10n_th_amount_to_text-14.0.1.0.1.dev6.dist-info/METADATA
odoo14_addon_l10n_th_amount_to_text-14.0.1.0.1.dev6.dist-info/WHEEL
odoo14_addon_l10n_th_amount_to_text-14.0.1.0.1.dev6.dist-info/top_level.txt
odoo14_addon_l10n_th_amount_to_text-14.0.1.0.1.dev6.dist-info/RECORD
